script_launcher_ui/__init__.py
script_launcher_ui/ui_library.py
script_launcher_ui-0.1.0.dist-info/LICENSE
script_launcher_ui-0.1.0.dist-info/METADATA
script_launcher_ui-0.1.0.dist-info/WHEEL
script_launcher_ui-0.1.0.dist-info/top_level.txt
script_launcher_ui-0.1.0.dist-info/RECORD
